{
    "service_request_id": "UN201708010302",
    "requested_datetime": "2017-08-01 14:27:00",
    "status": "已完工",
    "keyword": {},
    "area": "中西區",
    "service_name": "違規停車",
    "agency": "臺南市政府警察局勤務指揮中心",
    "subproject": "違規停車",
    "description": "中西區友愛街253號 違規停車",
    "address_string": "700台灣台南市中西區友愛街253號",
    "lat": "22.992081714679383",
    "long": "120.19657697528599",
    "service_notice": {},
    "updated_datetime": "2017-08-01 16:03:46",
    "expected_datetime": "2017-08-01 14:27:00"
}