{
    "service_request_id": "UN201610110091",
    "requested_datetime": "2016-10-11 10:07:00",
    "status": "已完工",
    "keyword": {},
    "area": "永康區",
    "service_name": "違規停車",
    "agency": "臺南市政府警察局勤務指揮中心",
    "subproject": "違規停車",
    "description": "永康區中正六街沿線(正南五街到正南五街410巷)  違規停車",
    "address_string": "永康區中正六街沿線",
    "lat": "23.036660687181605",
    "long": "120.23750748485327",
    "service_notice": {},
    "updated_datetime": "2016-10-11 16:25:01",
    "expected_datetime": "2016-10-11 10:07:00"
}