{
    "service_request_id": "UN201608240804",
    "requested_datetime": "2016-08-24 21:32:00",
    "status": "已完工",
    "keyword": {},
    "area": "新營區",
    "service_name": "違規停車",
    "agency": "臺南市政府警察局勤務指揮中心",
    "subproject": "違規停車",
    "description": "新營區民治路40號  違規停車",
    "address_string": "730台灣台南市新營區民治路40號",
    "lat": "23.31069080161239",
    "long": "120.31469064775884",
    "service_notice": {},
    "updated_datetime": "2016-08-25 03:16:57",
    "expected_datetime": "2016-08-24 21:32:00"
}