{
    "service_request_id": "UN201702150324",
    "requested_datetime": "2017-02-15 19:22:00",
    "status": "已完工",
    "keyword": {},
    "area": "佳里區",
    "service_name": "違規停車",
    "agency": "臺南市政府警察局勤務指揮中心",
    "subproject": "違規停車",
    "description": "佳里區忠孝東路59-77號  違規停車",
    "address_string": "722台灣台南市佳里區忠孝東路59-77號",
    "lat": "23.164981166263313",
    "long": "120.17917285026238",
    "service_notice": {},
    "updated_datetime": "2017-02-16 06:55:26",
    "expected_datetime": "2017-02-15 19:22:00"
}