{
    "service_request_id": "UN201511080258",
    "requested_datetime": "2015-11-08 23:11:00",
    "status": "未處理",
    "keyword": {},
    "area": "中西區",
    "service_name": "騎樓舉發",
    "agency": "臺南市政府警察局勤務指揮中心",
    "subproject": "騎樓舉發",
    "description": "中西區尊王路*海安路一段 \/ 尊王路*海安路一段滷味店旁 \/ 尊王路*海安路一段對面",
    "address_string": "中西區尊王路*海安路一段 \/ 尊王路*海安路一段滷味店旁 \/ 尊王路*海安路一段對面",
    "lat": {},
    "long": {},
    "service_notice": {},
    "updated_datetime": {},
    "expected_datetime": "2015-11-15 23:11:00"
}