{
    "service_request_id": "UN201601230273",
    "requested_datetime": "2016-01-23 20:20:00",
    "status": "已完工",
    "keyword": {},
    "area": "中西區",
    "service_name": "違規停車",
    "agency": "臺南市政府警察局第二分局,臺南市政府警察局勤務指揮中心",
    "subproject": "違規停車",
    "description": "中西區府緯四巷27號旁違規停車",
    "address_string": "700台灣台南市中西區府緯四巷27號旁",
    "lat": "22.983950620767143",
    "long": "120.19895005971193",
    "service_notice": {},
    "updated_datetime": "2016-01-27 09:59:28",
    "expected_datetime": "2016-01-23 20:20:00"
}