{
    "service_request_id": "UN201512170650",
    "requested_datetime": "2015-12-17 21:22:00",
    "status": "已完工",
    "keyword": {},
    "area": "永康區",
    "service_name": "違規停車",
    "agency": "臺南市政府警察局,臺南市政府警察局勤務指揮中心",
    "subproject": "違規停車",
    "description": "永康區南台街10巷3號 違規停車",
    "address_string": "710台灣台南市永康區南台街10巷3號",
    "lat": "23.022874440939756",
    "long": "120.22368673235177",
    "service_notice": {},
    "updated_datetime": "2015-12-18 03:47:57",
    "expected_datetime": "2015-12-17 21:22:00"
}