{
    "service_request_id": "UN201707050143",
    "requested_datetime": "2017-07-05 12:25:00",
    "status": "已完工",
    "keyword": {},
    "area": "中西區",
    "service_name": "違規停車",
    "agency": "臺南市政府警察局勤務指揮中心",
    "subproject": "違規停車",
    "description": "中西區西門路一段468號-476號  違停",
    "address_string": "中西區西門路一段468號-476號",
    "lat": "22.9832127",
    "long": "120.1976981",
    "service_notice": {},
    "updated_datetime": "2017-07-05 16:22:46",
    "expected_datetime": "2017-07-12 12:25:00"
}