{
    "service_request_id": "UN201611080310",
    "requested_datetime": "2016-11-08 18:13:00",
    "status": "已完工",
    "keyword": {},
    "area": "中西區",
    "service_name": "違規停車",
    "agency": "臺南市政府警察局勤務指揮中心",
    "subproject": "違規停車",
    "description": "中西區西門路二段25巷 違規停車",
    "address_string": "中西區西門路二段25巷",
    "lat": "22.990673358716858",
    "long": "120.19774501521329",
    "service_notice": {},
    "updated_datetime": "2016-11-08 22:23:11",
    "expected_datetime": "2016-11-08 18:13:00"
}