{
    "service_request_id": "UN201703090243",
    "requested_datetime": "2017-03-09 18:10:00",
    "status": "已完工",
    "keyword": {},
    "area": "東區",
    "service_name": "違規停車",
    "agency": "臺南市政府警察局勤務指揮中心",
    "subproject": "違規停車",
    "description": "東區勝利路294號 違規停車",
    "address_string": "No. 294, Shengli Rd, East District, Tainan City, Taiwan 701",
    "lat": "22.9988211",
    "long": "120.2178242",
    "service_notice": {},
    "updated_datetime": "2017-03-09 23:13:34",
    "expected_datetime": "2017-03-09 18:10:00"
}