{
    "service_request_id": "UN201712030070",
    "requested_datetime": "2017-12-03 09:59:00",
    "status": "已完工",
    "keyword": {},
    "area": "永康區",
    "service_name": "噪音舉發",
    "agency": "臺南市政府都市發展局,臺南市政府環境保護局,臺南市政府警察局勤務指揮中心",
    "subproject": "場所連續噪音",
    "description": "永康區永大一路241號對面 連續噪音",
    "address_string": "永康區永大一路241號對面",
    "lat": "23.0165426",
    "long": "120.2554544",
    "service_notice": {},
    "updated_datetime": "2017-12-03 18:45:55",
    "expected_datetime": "2017-12-10 09:59:00"
}