{
    "service_request_id": "UN201601120294",
    "requested_datetime": "2016-01-12 19:14:00",
    "status": "已完工",
    "keyword": {},
    "area": "歸仁區",
    "service_name": "違規停車",
    "agency": "臺南市政府警察局勤務指揮中心,臺南市政府警察局歸仁分局",
    "subproject": "違規停車",
    "description": "歸仁衛生所旁 違規停車",
    "address_string": "711台灣台南市歸仁區中正北路一段11號歸仁衛生所旁",
    "lat": "22.9671503",
    "long": "120.2940496",
    "service_notice": {},
    "updated_datetime": "2016-01-14 09:27:30",
    "expected_datetime": "2016-01-12 19:14:00"
}