{
    "service_request_id": "UN201710210159",
    "requested_datetime": "2017-10-21 13:13:00",
    "status": "已完工",
    "keyword": {},
    "area": "安平區",
    "service_name": "噪音舉發",
    "agency": "臺南市政府研究發展考核委員會",
    "subproject": "場所連續噪音",
    "description": "測試A-TB-2017-65086安平區國勝路82號 噪音舉發",
    "address_string": "安平區國勝路82號",
    "lat": "23.0015093",
    "long": "120.1606244",
    "service_notice": {},
    "updated_datetime": "2017-10-24 08:14:34",
    "expected_datetime": "2017-10-21 13:13:00"
}