{
    "service_request_id": "UN201611230257",
    "requested_datetime": "2016-11-23 17:29:00",
    "status": "已完工",
    "keyword": {},
    "area": "中西區",
    "service_name": "違規停車",
    "agency": "臺南市政府警察局第二分局,臺南市政府警察局勤務指揮中心",
    "subproject": "違規停車",
    "description": "中西區府前路二段192號 違規停車",
    "address_string": "中西區府前路二段192號",
    "lat": "22.9915882",
    "long": "120.1930382",
    "service_notice": {},
    "updated_datetime": "2016-11-25 09:59:54",
    "expected_datetime": "2016-11-23 17:29:00"
}