{
    "service_request_id": "UN201610100243",
    "requested_datetime": "2016-10-10 17:38:00",
    "status": "已完工",
    "keyword": {},
    "area": "永康區",
    "service_name": "違規停車",
    "agency": "臺南市政府警察局勤務指揮中心",
    "subproject": "違規停車",
    "description": "永康區中正北路沿線  違規停車",
    "address_string": "永康區中正北路沿線",
    "lat": "23.041395141345582",
    "long": "120.23954998701811",
    "service_notice": {},
    "updated_datetime": "2016-10-10 19:08:34",
    "expected_datetime": "2016-10-10 17:38:00"
}